regsets/__init__.py
regsets-0.1.2.dist-info/LICENSE
regsets-0.1.2.dist-info/METADATA
regsets-0.1.2.dist-info/WHEEL
regsets-0.1.2.dist-info/top_level.txt
regsets-0.1.2.dist-info/RECORD
