Metadata-Version: 2.1
Name: regsets
Version: 0.1.2
Summary: A collection of regression datasets with PyTorch-like dataset classes.
Author-email: Pin-Yen Huang <pyhuang97@gmail.com>
License: MIT License
Project-URL: Homepage, https://github.com/pm25/regression-datasets
Project-URL: Repository, https://github.com/pm25/regression-datasets.git
Project-URL: Issues, https://github.com/pm25/regression-datasets/issues
Keywords: regression,dataset,pytorch
Classifier: Programming Language :: Python :: 3
Classifier: License :: OSI Approved :: MIT License
Classifier: Operating System :: OS Independent
Requires-Python: >=3.7
License-File: LICENSE
Requires-Dist: librosa>=0.10.1
Requires-Dist: numpy>=1.24.4
Requires-Dist: pandas>=2.0.3
Requires-Dist: Pillow>=9.0.0
Requires-Dist: torch>=1.12.0
Requires-Dist: torchvision>=0.13.0
Requires-Dist: tqdm
